a_cv2_calculate_difference/LICENSE
a_cv2_calculate_difference/README.MD
a_cv2_calculate_difference/__init__.py
a_cv2_calculate_difference/requirements.txt
a_cv2_calculate_difference/thirdparty.json
a_cv2_calculate_difference-0.10.dist-info/LICENSE.rst
a_cv2_calculate_difference-0.10.dist-info/METADATA
a_cv2_calculate_difference-0.10.dist-info/WHEEL
a_cv2_calculate_difference-0.10.dist-info/top_level.txt
a_cv2_calculate_difference-0.10.dist-info/RECORD
