Metadata-Version: 2.1
Name: a-cv2-calculate-difference
Version: 0.10
Summary: Calculates the difference between 2 images
Home-page: https://github.com/hansalemaos/a_cv2_calculate_difference
Author: Johannes Fischer
Author-email: <aulasparticularesdealemaosp@gmail.com>
License: MIT
Keywords: OpenCV,cv2,images,pixels,detection
Classifier: Development Status :: 4 - Beta
Classifier: Programming Language :: Python :: 3 :: Only
Classifier: Programming Language :: Python :: 3.9
Classifier: Topic :: Scientific/Engineering :: Visualization
Classifier: Topic :: Software Development :: Libraries :: Python Modules
Classifier: Topic :: Text Editors :: Text Processing
Classifier: Topic :: Text Processing :: General
Classifier: Topic :: Text Processing :: Indexing
Classifier: Topic :: Text Processing :: Filters
Classifier: Topic :: Utilities
License-File: LICENSE.rst
Requires-Dist: a-cv2-imshow-thread
Requires-Dist: a-cv-imwrite-imread-plus
Requires-Dist: opencv-python
